ricochet/__init__.py
ricochet/autowired.py
ricochet/dependency.py
ricochet/exceptions.py
ricochet/remarks.py
ricochet/scopes.py
ricochet/injection/__init__.py
ricochet/injection/base_dependency_injector.py
ricochet/injection/dependency_injector.py
ricochet/objectlet_registries/__init__.py
ricochet/objectlet_registries/base_dual_registry_mediator.py
ricochet/objectlet_registries/base_prototype_registry.py
ricochet/objectlet_registries/base_registry.py
ricochet/objectlet_registries/base_singleton_registry.py
ricochet/objectlet_registries/impl/__init__.py
ricochet/objectlet_registries/impl/dual_registry_mediator.py
ricochet/objectlet_registries/impl/prototype_registry.py
ricochet/objectlet_registries/impl/singleton_registry.py
ricochet/utils/__init__.py
ricochet/utils/abc_mock.py
ricochet/utils/hints.py
ricochet/utils/logger_mixin.py
ricochet-0.2.1.dist-info/LICENSE
ricochet-0.2.1.dist-info/METADATA
ricochet-0.2.1.dist-info/WHEEL
ricochet-0.2.1.dist-info/top_level.txt
ricochet-0.2.1.dist-info/RECORD
