Metadata-Version: 2.1
Name: ricochet
Version: 0.2.1
Summary: Simple Spring-inspired IoC framework for Python.
Home-page: UNKNOWN
License: UNKNOWN
Keywords: python ioc spring inversion of control
Platform: UNKNOWN
Classifier: Development Status :: 2 - Pre-Alpha
Classifier: Intended Audience :: Developers
Classifier: Topic :: Software Development
Classifier: Topic :: Software Development :: Libraries :: Python Modules
Classifier: Topic :: Utilities
Classifier: License :: OSI Approved :: MIT License
Classifier: Natural Language :: English
Classifier: Operating System :: OS Independent
Classifier: Programming Language :: Python :: 3.7
Requires-Python: >=3.7.0
Requires-Dist: metabeyond (>=0.2.0)
Provides-Extra: deploy
Requires-Dist: twine ; extra == 'deploy'
Requires-Dist: black ; extra == 'deploy'
Requires-Dist: wheel ; extra == 'deploy'
Requires-Dist: setuptools ; extra == 'deploy'
Provides-Extra: develop
Requires-Dist: metabeyond (>=0.2.0) ; extra == 'develop'
Provides-Extra: docs
Requires-Dist: sphinx ; extra == 'docs'
Requires-Dist: graphviz ; extra == 'docs'
Requires-Dist: Jinja2 ; extra == 'docs'
Requires-Dist: solar-theme ; extra == 'docs'
Requires-Dist: sphinxcontrib-fulltoc ; extra == 'docs'
Requires-Dist: sphinx-autodoc-typehints ; extra == 'docs'
Requires-Dist: sphinxcontrib-asyncio ; extra == 'docs'
Provides-Extra: lint
Requires-Dist: pylint ; extra == 'lint'
Provides-Extra: sast
Requires-Dist: bandit ; extra == 'sast'
Provides-Extra: test
Requires-Dist: coverage ; extra == 'test'
Requires-Dist: asynctest ; extra == 'test'
